json_operations/__init__.py
json_operations-2.6.0.dist-info/LICENSE.md
json_operations-2.6.0.dist-info/METADATA
json_operations-2.6.0.dist-info/WHEEL
json_operations-2.6.0.dist-info/top_level.txt
json_operations-2.6.0.dist-info/RECORD
