Metadata-Version: 2.1
Name: json-operations
Version: 2.6.0
Summary: Specify function operations is JSON
Home-page: https://github.com/cedar-team/json-operations
Author: Cedar
Author-email: 
License: MIT
Classifier: Programming Language :: Python :: 3
Classifier: License :: OSI Approved :: MIT License
Classifier: Operating System :: OS Independent
Requires-Python: >=3.6
License-File: LICENSE.md
Provides-Extra: test
Requires-Dist: parameterized (==0.8.1) ; extra == 'test'
Requires-Dist: black (==22.8.0) ; extra == 'test'
Requires-Dist: isort (==5.10.1) ; extra == 'test'
